Metadata-Version: 2.1
Name: pjdtextblob
Version: 0.17.2
Summary: Simple, Pythonic text processing. Sentiment analysis, part-of-speech tagging, noun phrase parsing, and more.
Home-page: https://github.com/prakashdale/TextBlob
Author: Prakash Dale
Author-email: prakashdale@gmail.com
License: MIT
Keywords: textblob,nlp,linguistics,nltk,pattern
Platform: UNKNOWN
Classifier: Intended Audience :: Developers
Classifier: Natural Language :: English
Classifier: License :: OSI Approved :: MIT License
Classifier: Programming Language :: Python
Classifier: Programming Language :: Python :: 2.7
Classifier: Programming Language :: Python :: 3.5
Classifier: Programming Language :: Python :: 3.6
Classifier: Programming Language :: Python :: 3.7
Classifier: Programming Language :: Python :: 3.8
Classifier: Programming Language :: Python :: Implementation :: CPython
Classifier: Programming Language :: Python :: Implementation :: PyPy
Classifier: Topic :: Text Processing :: Linguistic
License-File: LICENSE
License-File: NOTICE
License-File: AUTHORS.rst
Requires-Dist: nltk (<3.5,>=3.1) ; python_version < "3"
Requires-Dist: nltk (>=3.1) ; python_version >= "3"
